witchhazel.py
witchhazel-2022.9.8.dist-info/LICENSE
witchhazel-2022.9.8.dist-info/METADATA
witchhazel-2022.9.8.dist-info/WHEEL
witchhazel-2022.9.8.dist-info/entry_points.txt
witchhazel-2022.9.8.dist-info/top_level.txt
witchhazel-2022.9.8.dist-info/RECORD
